sourceline.cp39-win_amd64.pyd
sourceline-0.0.4.dist-info/LICENSE
sourceline-0.0.4.dist-info/METADATA
sourceline-0.0.4.dist-info/WHEEL
sourceline-0.0.4.dist-info/top_level.txt
sourceline-0.0.4.dist-info/RECORD
